setup.cfg
setup.py
comdet/__init__.py
comdet/comdet.py
comdet/community.py
comdet/wrapper.py
comdet.egg-info/PKG-INFO
comdet.egg-info/SOURCES.txt
comdet.egg-info/dependency_links.txt
comdet.egg-info/not-zip-safe
comdet.egg-info/top_level.txt