Metadata-Version: 1.0
Name: comdet
Version: 0.3
Summary: comdet is used to detect community among graph nodes. Its based on lovain method
Home-page: http://github.com/pankajr141/comdet
Author: Pankaj Rawat
Author-email: pankajr141@gmail.com
License: MIT
Platform: UNKNOWN
